minesweeper_env_rl/__init__.py
minesweeper_env_rl/record.py
minesweeper_env_rl/stress_bench.py
minesweeper_env_rl/ui_minesweeper.py
minesweeper_env_rl/env/__init__.py
minesweeper_env_rl/env/pomdp.py
minesweeper_env_rl/env/visualization.py
minesweeper_env_rl-0.12.0.dist-info/METADATA
minesweeper_env_rl-0.12.0.dist-info/WHEEL
minesweeper_env_rl-0.12.0.dist-info/top_level.txt
minesweeper_env_rl-0.12.0.dist-info/RECORD
