Metadata-Version: 2.4
Name: minesweeper-env-rl
Version: 0.12.0
Summary: JAX Minesweeper environment for reinforcement learning agents.
Keywords: reinforcement-learning,jax,minesweeper
Requires-Python: >=3.10
Requires-Dist: altair==5.5.0
Requires-Dist: attrs==25.4.0
Requires-Dist: blinker==1.9.0
Requires-Dist: cachetools==6.2.0
Requires-Dist: certifi==2025.10.5
Requires-Dist: charset-normalizer==3.4.3
Requires-Dist: click==8.3.0
Requires-Dist: colorama==0.4.6
Requires-Dist: contourpy==1.3.3
Requires-Dist: cycler==0.12.1
Requires-Dist: fonttools==4.60.1
Requires-Dist: gitdb==4.0.12
Requires-Dist: GitPython==3.1.45
Requires-Dist: idna==3.10
Requires-Dist: imageio==2.37.0
Requires-Dist: imageio-ffmpeg==0.6.0
Requires-Dist: jax==0.7.2
Requires-Dist: jaxlib==0.7.2
Requires-Dist: Jinja2==3.1.6
Requires-Dist: jsonschema==4.25.1
Requires-Dist: jsonschema-specifications==2025.9.1
Requires-Dist: kiwisolver==1.4.9
Requires-Dist: MarkupSafe==3.0.3
Requires-Dist: matplotlib==3.10.6
Requires-Dist: ml_dtypes==0.5.3
Requires-Dist: narwhals==2.7.0
Requires-Dist: numpy==2.3.3
Requires-Dist: opt_einsum==3.4.0
Requires-Dist: packaging==25.0
Requires-Dist: pandas==2.3.3
Requires-Dist: pillow==11.3.0
Requires-Dist: protobuf==6.32.1
Requires-Dist: pyarrow==21.0.0
Requires-Dist: pydeck==0.9.1
Requires-Dist: pyparsing==3.2.5
Requires-Dist: python-dateutil==2.9.0.post0
Requires-Dist: pytz==2025.2
Requires-Dist: referencing==0.36.2
Requires-Dist: requests==2.32.5
Requires-Dist: rpds-py==0.27.1
Requires-Dist: scipy==1.16.2
Requires-Dist: six==1.17.0
Requires-Dist: smmap==5.0.2
Requires-Dist: streamlit==1.50.0
Requires-Dist: streamlit-image-coordinates==0.4.0
Requires-Dist: tenacity==9.1.2
Requires-Dist: toml==0.10.2
Requires-Dist: tornado==6.5.2
Requires-Dist: typing_extensions==4.15.0
Requires-Dist: tzdata==2025.2
Requires-Dist: urllib3==2.5.0
Requires-Dist: watchdog==6.0.0
